mintzy/__init__.py
mintzy/client.py
mintzy-0.1.6.dist-info/METADATA
mintzy-0.1.6.dist-info/WHEEL
mintzy-0.1.6.dist-info/top_level.txt
mintzy-0.1.6.dist-info/RECORD
