Metadata-Version: 2.4
Name: mintzy
Version: 0.1.6
Summary: Mintzy SDK for stock price prediction
Author: Om Kulthe 
Author-email: mintzy01.ai@gmail.com
Classifier: Programming Language :: Python :: 3
Classifier: License :: OSI Approved :: MIT License
Requires-Python: >=3.7
Requires-Dist: requests>=2.25.0
Dynamic: author
Dynamic: author-email
Dynamic: classifier
Dynamic: requires-dist
Dynamic: requires-python
Dynamic: summary
